<annotation>
	<folder>test</folder>
	<filename>800px-Berlin_Omnibus_Linie_100_Doppeldecker.JPG</filename>
	<path>C:\tensorflow1\models\research\object_detection\images\test\800px-Berlin_Omnibus_Linie_100_Doppeldecker.JPG</path>
	<source>
		<database>Unknown</database>
	</source>
	<size>
		<width>800</width>
		<height>600</height>
		<depth>3</depth>
	</size>
	<segmented>0</segmented>
	<object>
		<name>bus</name>
		<pose>Unspecified</pose>
		<truncated>0</truncated>
		<difficult>0</difficult>
		<bndbox>
			<xmin>27</xmin>
			<ymin>56</ymin>
			<xmax>663</xmax>
			<ymax>491</ymax>
		</bndbox>
	</object>
	<object>
		<name>car</name>
		<pose>Unspecified</pose>
		<truncated>0</truncated>
		<difficult>0</difficult>
		<bndbox>
			<xmin>640</xmin>
			<ymin>327</ymin>
			<xmax>797</xmax>
			<ymax>446</ymax>
		</bndbox>
	</object>
</annotation>
